gempaterbaru/__init__.py
Newestearthquake_Indonesia_BMKG-0.3.dist-info/LICENSE
Newestearthquake_Indonesia_BMKG-0.3.dist-info/METADATA
Newestearthquake_Indonesia_BMKG-0.3.dist-info/WHEEL
Newestearthquake_Indonesia_BMKG-0.3.dist-info/top_level.txt
Newestearthquake_Indonesia_BMKG-0.3.dist-info/RECORD
