Metadata-Version: 2.1
Name: Newestearthquake-Indonesia-BMKG
Version: 0.3
Summary: This package will get the latest earthquake from BMKG | Meteorological, Climatological, and Geophysical Agency.
Home-page: https://github.com/Apatheia8/latest-Indonesia-earthquake
Author: Deni Rahmawan
Author-email: denirahmawan17@gmail.com
Classifier: Programming Language :: Python :: 3
Classifier: License :: OSI Approved :: GNU General Public License v3 (GPLv3)
Classifier: Operating System :: OS Independent
Classifier: Development Status :: 5 - Production/Stable
Requires-Python: >=3.6
License-File: LICENSE
